deploya/__init__.py
deploya-0.0.1.dist-info/LICENSE
deploya-0.0.1.dist-info/METADATA
deploya-0.0.1.dist-info/WHEEL
deploya-0.0.1.dist-info/top_level.txt
deploya-0.0.1.dist-info/RECORD
