Metadata-Version: 2.1
Name: deploya
Version: 0.0.1
Summary: Library for interfacing with deploya.io
Home-page: https://www.algosquare.io
Author: Deploya contributers
Author-email: contact@algosquare.io
License: MIT License
Keywords: deploya,tools,api
Platform: UNKNOWN
Classifier: Programming Language :: Python :: 3
Classifier: License :: OSI Approved :: MIT License
Classifier: Operating System :: OS Independent
License-File: LICENSE
Provides-Extra: full
Requires-Dist: requests ; extra == 'full'
Requires-Dist: numpy ; extra == 'full'
Requires-Dist: scikit-learn ; extra == 'full'
Requires-Dist: pandas ; extra == 'full'
